LICENSE
MANIFEST.in
README.md
requirements.txt
runtests.py
setup.py
pagarme/__init__.py
pagarme/api.py
pagarme/config.py
pagarme/exceptions.py
pagarme/common/__init__.py
pagarme/common/enum.py
pagarme/common/util.py
pagarme/resources/__init__.py
pagarme/resources/bank_account.py
pagarme/resources/card.py
pagarme/resources/card_hash.py
pagarme/resources/customer.py
pagarme/resources/payment.py
pagarme/resources/plan.py
pagarme/resources/recipient.py
pagarme/resources/resource.py
pagarme/resources/search.py
pagarme/resources/subscription.py
pagarme/resources/transaction.py
pagarme/resources/zipcode.py
pagarmepy.egg-info/PKG-INFO
pagarmepy.egg-info/SOURCES.txt
pagarmepy.egg-info/dependency_links.txt
pagarmepy.egg-info/not-zip-safe
pagarmepy.egg-info/requires.txt
pagarmepy.egg-info/top_level.txt
tests/__init__.py
tests/test_api.py
tests/test_bank_account.py
tests/test_card.py
tests/test_card_hash.py
tests/test_customer.py
tests/test_payment.py
tests/test_plan.py
tests/test_recipient.py
tests/test_resource.py
tests/test_subscription.py
tests/test_transaction.py
tests/test_zipcode.py