Metadata-Version: 1.1
Name: pagarmepy
Version: 1.0.1
Summary: Pagar.me Python API wrapper
Home-page: https://github.com/michaeltcoelho/pagarme.py
Author: Michael Coelho
Author-email: michael.tcoelho@gmail.com
License: MIT License
Download-URL: https://github.com/michaeltcoelho/pagarme.py
Keywords: pagarme,payment,gateway,api,wrapper
Platform: UNKNOWN
Classifier: Development Status :: 3 - Alpha
Classifier: Environment :: Web Environment
Classifier: Intended Audience :: Developers
Classifier: Natural Language :: English
Classifier: License :: OSI Approved :: BSD License
Classifier: Programming Language :: Python
Classifier: Programming Language :: Python :: 2
Classifier: Programming Language :: Python :: 2.6
Classifier: Programming Language :: Python :: 2.7
